Topsis_Pranav_102003432/Pranav_102003432.py
Topsis_Pranav_102003432-0.13.dist-info/METADATA
Topsis_Pranav_102003432-0.13.dist-info/WHEEL
Topsis_Pranav_102003432-0.13.dist-info/entry_points.txt
Topsis_Pranav_102003432-0.13.dist-info/top_level.txt
Topsis_Pranav_102003432-0.13.dist-info/RECORD
