Metadata-Version: 2.1
Name: Topsis-Pranav-102003432
Version: 0.13
Summary: This is a topsis package of version 0.13
Home-page: UNKNOWN
Author: Pranav Singh
Author-email: psingh2_be20@thapar.edu
License: UNKNOWN
Platform: UNKNOWN
Requires-Dist: pandas
